control_plane_cage_client/__init__.py
control_plane_cage_client/api/__init__.py
control_plane_cage_client/api/collaboration_spaces/__init__.py
control_plane_cage_client/api/collaboration_spaces/get_collaborator.py
control_plane_cage_client/api/collaboration_spaces/get_collaborators.py
control_plane_cage_client/api/data_contracts/__init__.py
control_plane_cage_client/api/data_contracts/get_data_contract.py
control_plane_cage_client/client.py
control_plane_cage_client/errors.py
control_plane_cage_client/models/__init__.py
control_plane_cage_client/models/abstract_collaborator.py
control_plane_cage_client/models/abstract_collaborator_configuration.py
control_plane_cage_client/models/abstract_data_contract.py
control_plane_cage_client/models/abstract_data_contract_api_version.py
control_plane_cage_client/models/abstract_data_contract_kind.py
control_plane_cage_client/models/abstract_property.py
control_plane_cage_client/models/abstract_property_logical_type.py
control_plane_cage_client/models/abstract_property_logical_type_options.py
control_plane_cage_client/models/abstract_schema.py
control_plane_cage_client/models/abstract_schema_logical_type.py
control_plane_cage_client/models/algo_source.py
control_plane_cage_client/models/any_type_type_5.py
control_plane_cage_client/models/api_server.py
control_plane_cage_client/models/authoritative_definition.py
control_plane_cage_client/models/code_provider.py
control_plane_cage_client/models/code_provider_role.py
control_plane_cage_client/models/code_provider_settings.py
control_plane_cage_client/models/collaborator.py
control_plane_cage_client/models/cron.py
control_plane_cage_client/models/custom_property.py
control_plane_cage_client/models/custom_server.py
control_plane_cage_client/models/data_consumer.py
control_plane_cage_client/models/data_consumer_role.py
control_plane_cage_client/models/data_consumer_settings.py
control_plane_cage_client/models/data_contract.py
control_plane_cage_client/models/data_contract_dv.py
control_plane_cage_client-0.5.0.dist-info/METADATA
control_plane_cage_client-0.5.0.dist-info/WHEEL
control_plane_cage_client-0.5.0.dist-info/RECORD
